CHANGELOG.txt
LICENCE.txt
MANIFEST.in
README.txt
main.py
setup.py
basicalc.egg-info/PKG-INFO
basicalc.egg-info/SOURCES.txt
basicalc.egg-info/dependency_links.txt
basicalc.egg-info/top_level.txt